py_cord_components/__init__.py
py_cord_components/client.py
py_cord_components/component.py
py_cord_components/const.py
py_cord_components/dpy_overrides.py
py_cord_components/http.py
py_cord_components/interaction.py
py_cord_components/utils.py
py_cord_components/ext/filters.py
py_cord_components-2.2.3.dist-info/LICENSE
py_cord_components-2.2.3.dist-info/METADATA
py_cord_components-2.2.3.dist-info/WHEEL
py_cord_components-2.2.3.dist-info/top_level.txt
py_cord_components-2.2.3.dist-info/RECORD
