Metadata-Version: 2.1
Name: py-cord-components
Version: 2.2.3
Summary: An unofficial library for py-cord components.
Home-page: https://github.com/spacedev-official/py-cord-components
Author: SpaceDev
Author-email: support@spacedev.space
License: MIT License
Platform: UNKNOWN
Classifier: Intended Audience :: Developers
Classifier: License :: OSI Approved :: MIT License
Classifier: Natural Language :: English
Classifier: Operating System :: OS Independent
Classifier: Programming Language :: Python :: 3
Classifier: Programming Language :: Python :: 3.6
Classifier: Programming Language :: Python :: 3.7
Classifier: Programming Language :: Python :: 3.8
Classifier: Programming Language :: Python :: 3.9
Classifier: Topic :: Internet
Classifier: Topic :: Software Development :: Libraries :: Python Modules
Classifier: Topic :: Software Development :: Libraries
Classifier: Topic :: Utilities
Requires-Python: >=3.6
Requires-Dist: py-cord
Requires-Dist: aiohttp
Provides-Extra: dev
Requires-Dist: black ; extra == 'dev'
Requires-Dist: flake8 ; extra == 'dev'
Requires-Dist: isort ; extra == 'dev'
Requires-Dist: sphinx ; extra == 'dev'
Requires-Dist: sphinx-rtd-theme ; extra == 'dev'
Provides-Extra: lint
Requires-Dist: black ; extra == 'lint'
Requires-Dist: flake8 ; extra == 'lint'
Requires-Dist: isort ; extra == 'lint'
Requires-Dist: sphinx ; extra == 'lint'
Requires-Dist: sphinx-rtd-theme ; extra == 'lint'
Provides-Extra: readthedocs
Requires-Dist: sphinx ; extra == 'readthedocs'
Requires-Dist: sphinx-rtd-theme ; extra == 'readthedocs'
